xraydlps/__init__.py
xraydlps/classify/__init__.py
xraydlps/classify/classify.py
xraydlps/data/lc_mod.pkl
xraydlps/data/lc_mod_full.pkl
xraydlps/data/lcs.pkl
xraydlps/data/sum_mod.pkl
xraydlps/data/sum_mod_full.pkl
xraydlps/plot/__init__.py
xraydlps/plot/plot.py
xraydlps/tools/__init__.py
xraydlps/tools/tools.py
xraydlps-1.0.0.dist-info/METADATA
xraydlps-1.0.0.dist-info/WHEEL
xraydlps-1.0.0.dist-info/top_level.txt
xraydlps-1.0.0.dist-info/RECORD
